pandascore/__init__.py
pandascore/__version__.py
pandascore/api.py
pandascore/client.py
pandascore/errors.py
pandascore/lol.py
pandascore/pandascore.py
pandascore/util.py
pandascore-0.2.0.dist-info/DESCRIPTION.rst
pandascore-0.2.0.dist-info/METADATA
pandascore-0.2.0.dist-info/RECORD
pandascore-0.2.0.dist-info/WHEEL
pandascore-0.2.0.dist-info/metadata.json
pandascore-0.2.0.dist-info/top_level.txt
